{
	"HMAC": {
		"methods": [
			"compiler_HMAC",
			"HM_algorithm",
			"HM_hexDigest",
			"HM_key",
			"HM_message",
			"new HMAC"
		]
	},
	"JWK": {
		"methods": [
			"compiler_JWK",
			"JWK_find",
			"new JWK"
		]
	},
	"JWT": {
		"methods": [
			"compiler_JWT",
			"JWT_generate",
			"JWT_getEncodedHMAC",
			"JWT_header",
			"JWT_key",
			"JWT_payload",
			"JWT_verify",
			"new JWT"
		]
	},
	"Utility": {
		"methods": [
			"base64UrlDecode",
			"base64UrlEncode",
			"compareCaseSensitive",
			"compiler_utility",
			"hexCharToNum",
			"hexToBlob",
			"toIntDate"
		]
	},
	"trash": {}
}